{
    "asset": {
        "format": "png",
        "id": "45074327306aa6fde8b8545d6a94ef23",
        "name": "screenshot_20260109_161112_0003.png",
        "path": "file:D:/BiShe/MyMAAProject/data/datasets/train/images/screenshot_20260109_161112_0003.png",
        "size": {
            "width": 1920,
            "height": 1080
        },
        "state": 2,
        "type": 1
    },
    "regions": [
        {
            "id": "VtCkr423oz",
            "type": "RECTANGLE",
            "tags": [
                "Resource_Collection_Button"
            ],
            "boundingBox": {
                "height": 101.73913043478261,
                "width": 129.98368678629691,
                "left": 734.4861337683524,
                "top": 959.1847826086957
            },
            "points": [
                {
                    "x": 734.4861337683524,
                    "y": 959.1847826086957
                },
                {
                    "x": 864.4698205546493,
                    "y": 959.1847826086957
                },
                {
                    "x": 864.4698205546493,
                    "y": 1060.9239130434783
                },
                {
                    "x": 734.4861337683524,
                    "y": 1060.9239130434783
                }
            ]
        },
        {
            "id": "vy2wSxkyhH",
            "type": "RECTANGLE",
            "tags": [
                "Return_Button"
            ],
            "boundingBox": {
                "height": 79.82608695652175,
                "width": 125.28548123980426,
                "left": 28.189233278955957,
                "top": 21.619565217391305
            },
            "points": [
                {
                    "x": 28.189233278955957,
                    "y": 21.619565217391305
                },
                {
                    "x": 153.4747145187602,
                    "y": 21.619565217391305
                },
                {
                    "x": 153.4747145187602,
                    "y": 101.44565217391305
                },
                {
                    "x": 28.189233278955957,
                    "y": 101.44565217391305
                }
            ]
        }
    ],
    "version": "2.2.0"
}