{
    "asset": {
        "format": "png",
        "id": "6d108a6fca4c69f907c908bf4c38414c",
        "name": "screenshot_20260109_165053_0021.png",
        "path": "file:D:/BiShe/MyMAAProject/data/datasets/train/images/screenshot_20260109_165053_0021.png",
        "size": {
            "width": 1920,
            "height": 1080
        },
        "state": 2,
        "type": 1
    },
    "regions": [
        {
            "id": "umdBu90aAb",
            "type": "RECTANGLE",
            "tags": [
                "LS-5_Button"
            ],
            "boundingBox": {
                "height": 122.08695652173914,
                "width": 300.68515497553017,
                "left": 1343.6867862969007,
                "top": 370.6630434782609
            },
            "points": [
                {
                    "x": 1343.6867862969007,
                    "y": 370.6630434782609
                },
                {
                    "x": 1644.3719412724308,
                    "y": 370.6630434782609
                },
                {
                    "x": 1644.3719412724308,
                    "y": 492.75
                },
                {
                    "x": 1343.6867862969007,
                    "y": 492.75
                }
            ]
        },
        {
            "id": "BkQL0AoXey",
            "type": "RECTANGLE",
            "tags": [
                "Return_Button"
            ],
            "boundingBox": {
                "height": 76.69565217391305,
                "width": 158.17292006525287,
                "left": 25.05709624796085,
                "top": 15.358695652173914
            },
            "points": [
                {
                    "x": 25.05709624796085,
                    "y": 15.358695652173914
                },
                {
                    "x": 183.23001631321372,
                    "y": 15.358695652173914
                },
                {
                    "x": 183.23001631321372,
                    "y": 92.05434782608695
                },
                {
                    "x": 25.05709624796085,
                    "y": 92.05434782608695
                }
            ]
        }
    ],
    "version": "2.2.0"
}