{
    "asset": {
        "format": "png",
        "id": "e64ddad4444173935768292a461440cf",
        "name": "screenshot_20260109_161134_0014.png",
        "path": "file:D:/BiShe/MyMAAProject/data/datasets/train/images/screenshot_20260109_161134_0014.png",
        "size": {
            "width": 1920,
            "height": 1080
        },
        "state": 2,
        "type": 1
    },
    "regions": [
        {
            "id": "fQBPLH4hPw",
            "type": "RECTANGLE",
            "tags": [
                "Resource_Collection_Button"
            ],
            "boundingBox": {
                "height": 115.82608695652175,
                "width": 198.89070146818923,
                "left": 707.862969004894,
                "top": 951.358695652174
            },
            "points": [
                {
                    "x": 707.862969004894,
                    "y": 951.358695652174
                },
                {
                    "x": 906.7536704730833,
                    "y": 951.358695652174
                },
                {
                    "x": 906.7536704730833,
                    "y": 1067.1847826086957
                },
                {
                    "x": 707.862969004894,
                    "y": 1067.1847826086957
                }
            ]
        },
        {
            "id": "JPbqH9ZHEo",
            "type": "RECTANGLE",
            "tags": [
                "Return_Button"
            ],
            "boundingBox": {
                "height": 87.65217391304348,
                "width": 169.13539967373575,
                "left": 25.05709624796085,
                "top": 18.48913043478261
            },
            "points": [
                {
                    "x": 25.05709624796085,
                    "y": 18.48913043478261
                },
                {
                    "x": 194.19249592169658,
                    "y": 18.48913043478261
                },
                {
                    "x": 194.19249592169658,
                    "y": 106.1413043478261
                },
                {
                    "x": 25.05709624796085,
                    "y": 106.1413043478261
                }
            ]
        }
    ],
    "version": "2.2.0"
}